canisius_cyb600_example/__init__.py
canisius_cyb600_example/main.py
csc_cyb600_huff4-1.0.4.data/scripts/say-hello-cyb600
csc_cyb600_huff4-1.0.4.dist-info/LICENSE
csc_cyb600_huff4-1.0.4.dist-info/METADATA
csc_cyb600_huff4-1.0.4.dist-info/WHEEL
csc_cyb600_huff4-1.0.4.dist-info/top_level.txt
csc_cyb600_huff4-1.0.4.dist-info/RECORD
