Metadata-Version: 2.2
Name: csc_cyb600_huff4
Version: 1.0.4
Author: Darnell Huff
Author-email: huff4@canisius.edu
License: Apache License Version 2.0
License-File: LICENSE
Requires-Dist: colorama
Dynamic: author
Dynamic: author-email
Dynamic: license
Dynamic: requires-dist
